openai_so_batch/__init__.py
openai_so_batch/batch.py
openai_so_batch/costs.py
openai_so_batch-0.1.1.dist-info/licenses/LICENSE
openai_so_batch-0.1.1.dist-info/METADATA
openai_so_batch-0.1.1.dist-info/WHEEL
openai_so_batch-0.1.1.dist-info/top_level.txt
openai_so_batch-0.1.1.dist-info/RECORD
