Metadata-Version: 2.4
Name: openai-so-batch
Version: 0.1.1
Summary: Python library for creating and managing OpenAI Structured Outputs batch API calls
Home-page: https://github.com/ollieglass/openai-so-batch
Author: Ollie Glass
Author-email: Ollie Glass <ollie@ollieglass.com>
Maintainer-email: Ollie Glass <ollie@ollieglass.com>
License-Expression: MIT
Project-URL: Homepage, https://github.com/ollieglass/openai-batch
Project-URL: Repository, https://github.com/ollieglass/openai-batch
Project-URL: Issues, https://github.com/ollieglass/openai-batch/issues
Keywords: openai,batch,api,async
Classifier: Development Status :: 3 - Alpha
Classifier: Intended Audience :: Developers
Classifier: Operating System :: OS Independent
Classifier: Programming Language :: Python :: 3
Classifier: Programming Language :: Python :: 3.8
Classifier: Programming Language :: Python :: 3.9
Classifier: Programming Language :: Python :: 3.10
Classifier: Programming Language :: Python :: 3.11
Classifier: Programming Language :: Python :: 3.12
Requires-Python: >=3.8
License-File: LICENSE
Requires-Dist: openai>=1.0.0
Requires-Dist: pydantic>=2.0.0
Requires-Dist: tiktoken>=0.5.0
Dynamic: author
Dynamic: home-page
Dynamic: license-file
Dynamic: requires-python
